stf_decomposition/__init__.py
stf_decomposition/stf_decomposition.py
stf_decomposition-0.1.2.dist-info/LICENSE.txt
stf_decomposition-0.1.2.dist-info/METADATA
stf_decomposition-0.1.2.dist-info/WHEEL
stf_decomposition-0.1.2.dist-info/top_level.txt
stf_decomposition-0.1.2.dist-info/RECORD
