Metadata-Version: 2.1
Name: stf-decomposition
Version: 0.1.2
Summary: STF: seasonal-trend decomposition using the Fast Fourier transform
Home-page: https://github.com/thodson-usgs/stf-decomposition
Author: Timothy O. Hodson
Author-email: thodson@usgs.gov
Project-URL: Bug Tracker, https://github.com/thodson-usgs/stf-decomposition/issues
Classifier: Programming Language :: Python :: 3
Classifier: License :: CC0 1.0 Universal (CC0 1.0) Public Domain Dedication
Classifier: Operating System :: OS Independent
Requires-Python: >=3.6
License-File: LICENSE.txt
